Metadata-Version: 1.0
Name: spamme
Version: 0.0.1
Summary: The trash clean utilities
Home-page: http://fake.usr.com
Author: Z.G.
Author-email: zg@fake.usr.cim
License: MIT
Platform: UNKNOWN
